geograypher/__init__.py
geograypher/cameras/__init__.py
geograypher/cameras/cameras.py
geograypher/cameras/derived_cameras.py
geograypher/cameras/rig_cameras.py
geograypher/cameras/segmentor.py
geograypher/constants.py
geograypher/entrypoints/__init__.py
geograypher/entrypoints/aggregate_images.py
geograypher/entrypoints/annotation_image_selection.py
geograypher/entrypoints/assemble_ortho_predictions.py
geograypher/entrypoints/chip_ortho.py
geograypher/entrypoints/label_polygons.py
geograypher/entrypoints/multiview_detections.py
geograypher/entrypoints/project_detections.py
geograypher/entrypoints/render_height_masks.py
geograypher/entrypoints/render_labels.py
geograypher/entrypoints/visualize.py
geograypher/meshes/__init__.py
geograypher/meshes/derived_meshes.py
geograypher/meshes/meshes.py
geograypher/predictors/__init__.py
geograypher/predictors/derived_segmentors.py
geograypher/predictors/ortho_segmentor.py
geograypher/predictors/segmentor.py
geograypher/utils/__init__.py
geograypher/utils/example_data.py
geograypher/utils/files.py
geograypher/utils/geometric.py
geograypher/utils/geospatial.py
geograypher/utils/image.py
geograypher/utils/indexing.py
geograypher/utils/io.py
geograypher/utils/numeric.py
geograypher/utils/parsing.py
geograypher/utils/prediction_metrics.py
geograypher/utils/test_utils.py
geograypher/utils/visualization.py
geograypher-0.4.0.dist-info/METADATA
geograypher-0.4.0.dist-info/WHEEL
geograypher-0.4.0.dist-info/licenses/LICENSE
geograypher-0.4.0.dist-info/RECORD
