Metadata-Version: 2.4
Name: geograypher
Version: 0.4.0
Summary: Enabling Geospatial Predictions from Individual Drone Images
License-File: LICENSE
Author: David Russell
Author-email: djrussell@ucdavis.edu
Requires-Python: >=3.9,<3.12
Classifier: Programming Language :: Python :: 3
Classifier: Programming Language :: Python :: 3.9
Classifier: Programming Language :: Python :: 3.10
Classifier: Programming Language :: Python :: 3.11
Requires-Dist: cchardet (>=2.1.7,<3.0.0)
Requires-Dist: chardet (>=5.2.0,<6.0.0)
Requires-Dist: geopandas (>=0.14.2,<0.15.0)
Requires-Dist: ipykernel (>=6.26.0,<7.0.0)
Requires-Dist: ipywidgets (>=8.1.1,<9.0.0)
Requires-Dist: piexif (>=1.1.3,<2.0.0)
Requires-Dist: pyembree (==0.1.12)
Requires-Dist: pyvista (>=0.42.2,<0.43.0)
Requires-Dist: rasterstats (>=0.19.0,<0.20.0)
Requires-Dist: rtree (>=1.4.0,<2.0.0)
Requires-Dist: scikit-image (>=0.21.0,<0.22.0)
Requires-Dist: scikit-learn (>=1.4.0,<2.0.0)
Requires-Dist: setcoverpy (>=0.9.1,<0.10.0)
Requires-Dist: tqdm (>=4.66.2,<5.0.0)
Requires-Dist: trame (>=3.2.8,<4.0.0)
Requires-Dist: trame-vtk (>=2.8.0,<3.0.0)
Requires-Dist: trame-vuetify (>=2.4.2,<3.0.0)
Requires-Dist: trimesh (==3.23.5)
Requires-Dist: ubelt (>=1.3.5,<2.0.0)
